scmg/__init__.py
scmg/data/standard_genes.csv
scmg/data/gene_names/human_genes.csv
scmg/data/gene_names/mouse_genes.csv
scmg/data/gene_names/orthologue_map_human2mouse_best.csv
scmg/data/gene_names/orthologue_map_human2mouse_unique.csv
scmg/data/gene_names/orthologue_map_mouse2human_best.csv
scmg/model/__init__.py
scmg/model/basic.py
scmg/model/causal_prediction.py
scmg/model/cell_type_search.py
scmg/model/contrastive_embedding.py
scmg/model/manifold_generation.py
scmg/preprocessing/__init__.py
scmg/preprocessing/data_standardization.py
scmg-1.0.2.dist-info/licenses/LICENSE
scmg-1.0.2.dist-info/METADATA
scmg-1.0.2.dist-info/WHEEL
scmg-1.0.2.dist-info/top_level.txt
scmg-1.0.2.dist-info/RECORD
