Metadata-Version: 2.4
Name: scmg
Version: 1.0.2
Summary: Single cell manifold generator
Author: Xingjie Pan
Requires-Python: >=3.8
License-File: LICENSE
Requires-Dist: numpy==1.26.4
Requires-Dist: matplotlib==3.8.4
Requires-Dist: pandas==1.5.3
Requires-Dist: scanpy==1.10.4
Requires-Dist: torch==2.3.1
Requires-Dist: datasets==2.20.0
Dynamic: license-file
